dcpoc/__init__.py
dcpoc/prime_numbers.py
pymspell-0.0.1.dist-info/LICENSE
pymspell-0.0.1.dist-info/METADATA
pymspell-0.0.1.dist-info/WHEEL
pymspell-0.0.1.dist-info/top_level.txt
pymspell-0.0.1.dist-info/RECORD
